Metadata-Version: 2.1
Name: tprint
Version: 1.0
Summary: Print python collections as tables
Home-page: https://github.com/tim-fi/tprint
Author: Tim Fischer
Author-email: tim.fischer98@hotmail.com
License: MIT
Platform: UNKNOWN
Classifier: Development Status :: 3 - Alpha
Classifier: Programming Language :: Python :: 3.6
Classifier: Programming Language :: Python :: 3.7
Classifier: Programming Language :: Python :: 3.8
Classifier: License :: OSI Approved :: MIT License
Requires-Python: >=3.7
